xdj_datamap/__init__.py
xdj_datamap/apps.py
xdj_datamap/conf.py
xdj_datamap/defaults.py
xdj_datamap/models.py
xdj_datamap/urls.py
xdj_datamap/migrations/__init__.py
xdj_datamap/views/__init__.py
xdj_datamap/views/field.py
xdj_datamap/views/map.py
xdj_datamap/views/model.py
xdj_datamap-0.0.5.dist-info/METADATA
xdj_datamap-0.0.5.dist-info/WHEEL
xdj_datamap-0.0.5.dist-info/top_level.txt
xdj_datamap-0.0.5.dist-info/RECORD
