Metadata-Version: 2.1
Name: xdj-datamap
Version: 0.0.5
Summary: a datamap for django
Home-page: https://gitee.com/xdjango/xdj_datamap.git
Author: 18580543261
Author-email: 595127207@qq.com
License: MIT Licence
Platform: UNKNOWN
Classifier: License :: OSI Approved :: MIT License
Classifier: Intended Audience :: Developers
Classifier: Operating System :: OS Independent
Classifier: Programming Language :: Python
Classifier: Programming Language :: Python :: 2
Classifier: Programming Language :: Python :: 2.6
Classifier: Programming Language :: Python :: 2.7
Classifier: Programming Language :: Python :: 3
Classifier: Programming Language :: Python :: 3.3
Classifier: Programming Language :: Python :: 3.4
Classifier: Programming Language :: Python :: 3.5
Classifier: Programming Language :: Python :: 3.6
Classifier: Programming Language :: Python :: 3.7
Classifier: Programming Language :: Python :: 3.8
Classifier: Programming Language :: Python :: 3.9
Classifier: Programming Language :: Python :: 3.10
Requires-Dist: Django (==3.2.3)
Requires-Dist: djangorestframework (==3.12.4)
Requires-Dist: xdj-utils (==0.0.4)
